{
  "slug": "disclosure-of-material-events-or-information",
  "title": "Disclosure of Material Events or Information",
  "hasYearFilter": true,
  "filterItems": ["2025-26", "2024-25", "2023-24", "2022-23", "2021-22", "2020-21", "2019-20", "2018-19", "2017-18"],
  "isActive": true,
  "sections": [
    {
      "title": "Disclosure of Material Events or Information",
      "documents": [
        {
          "title": "RIL – Reg 30 – Bagging of Order – Vikas",
          "date": "01/12/2025",
          "pdfUrl": "https://refex.co.in/wp-content/uploads/2025/12/2.RIL_NTPC_Order_Vikas_sd.pdf",
          "year": "2025-26"
        },
        {
          "title": "RIL – Reg 30 – Bagging of Order – NTPC Limited",
          "date": "29/11/2025",
          "pdfUrl": "https://refex.co.in/wp-content/uploads/2025/12/1.RIL_NTPC_Order_nov2025_sd.pdf",
          "year": "2025-26"
        },
        {
          "title": "RIL Reg 30 – GST Order – Chhattisgarh",
          "date": "28/11/2025",
          "pdfUrl": "https://refex.co.in/wp-content/uploads/2025/11/RIL_GST_Order_STX_Chattisgarh_Nov2025_sd-1.pdf",
          "year": "2025-26"
        },
        {
          "title": "RIL – Reg 30 – Bagging Of Order – NTPC Order",
          "date": "27/11/2025",
          "pdfUrl": "https://refex.co.in/wp-content/uploads/2025/11/RIL_NTPC_Order_SCPL_sd-1.pdf",
          "year": "2025-26"
        },
        {
          "title": "RIL-Reg.30 Intimation – Incorporation of Step Down Subsidiary Company",
          "date": "25/11/2025",
          "pdfUrl": "https://refex.co.in/wp-content/uploads/2025/11/RIL_STX_IntimationforIncorporation_VRPL_25112025-1.pdf",
          "year": "2025-26"
        },
        {
          "title": "RIL – Reg 30 – Acquisition of REPPL by VRPL",
          "date": "21/11/2025",
          "pdfUrl": "https://refex.co.in/wp-content/uploads/2025/11/RIL_STX_IntimationforAcquisition_RefexEngineer_19112025.pdf",
          "year": "2025-26"
        },
        {
          "title": "RIL – Reg 30 – ESOP – November FY26",
          "date": "21/11/2025",
          "pdfUrl": "https://refex.co.in/wp-content/uploads/2025/11/RIL_Reg30_ESOP_Nov2025_sd.pdf",
          "year": "2025-26"
        },
        {
          "title": "RIL-Reg.30 – Appointment of SMP",
          "date": "17/11/2025",
          "pdfUrl": "https://refex.co.in/wp-content/uploads/2025/11/Reg30SMPAppointmentIntimation.pdf",
          "year": "2025-26"
        },
        {
          "title": "RIL – Reg 30 – Bagging Of Order – Chhattisgarh Genco",
          "date": "14/11/2025",
          "pdfUrl": "https://refex.co.in/wp-content/uploads/2025/11/RIL_Chattisgarh_Genco.pdf",
          "year": "2025-26"
        },
        {
          "title": "RIL – Reg 30 – Bagging Of Order – Vikas NHAI",
          "date": "13/11/2025",
          "pdfUrl": "https://refex.co.in/wp-content/uploads/2025/11/RIL_NHAI_Order_Vikas_Nov2025_sd.pdf",
          "year": "2025-26"
        },
        {
          "title": "RIL – Reg 30 – Bagging Of Order – NTPC",
          "date": "07/11/2025",
          "pdfUrl": "https://refex.co.in/wp-content/uploads/2025/11/RIL_NTPC_Nov_sd.pdf",
          "year": "2025-26"
        },
        {
          "title": "RIL – Media Release Q2 FY26",
          "date": "05/11/2025",
          "pdfUrl": "https://refex.co.in/wp-content/uploads/2025/11/RIL_PressRelease_Q2FY26_final.pdf",
          "year": "2025-26"
        },
        {
          "title": "RIL-Reg. 30 Disclosure Outcome of Board Meeting",
          "date": "04/11/2025",
          "pdfUrl": "https://refex.co.in/wp-content/uploads/2025/11/RIL_OutcomeoftheBM_04112025_sd.pdf",
          "year": "2025-26"
        },
        {
          "title": "RIL – Dhansar, Jharkhand – Bagging of Order",
          "date": "24/10/2025",
          "pdfUrl": "https://refex.co.in/wp-content/uploads/2025/10/RIL_Jharkhand_Order_sd.pdf",
          "year": "2025-26"
        },
        {
          "title": "RIL-Reg.30 – Appointment of SMP",
          "date": "24/10/2025",
          "pdfUrl": "https://refex.co.in/wp-content/uploads/2025/10/RIL_Reg30_SMP_sd.pdf",
          "year": "2025-26"
        },
        {
          "title": "RIL – Allotment of Securities",
          "date": "03/10/2025",
          "pdfUrl": "https://refex.co.in/wp-content/uploads/2025/10/RIL_Intimation_STX_Reg30_Allotment_sd.pdf",
          "year": "2025-26"
        },
        {
          "title": "RIL- Closure of Trading Window- Q2 FY 2025-26",
          "date": "30/09/2025",
          "pdfUrl": "https://refex.co.in/wp-content/uploads/2025/09/RIL_Trading_Window_Closure_Notice_Q2FY26_30092025_sd.pdf",
          "year": "2025-26"
        },
        {
          "title": "RIL – VRPL Bagging of Order",
          "date": "24/09/2025",
          "pdfUrl": "https://refex.co.in/wp-content/uploads/2025/09/RIL_VRPL_STX_Intimation_Sep2025_sd.pdf",
          "year": "2025-26"
        },
        {
          "title": "RIL – Press Release",
          "date": "22/09/2025",
          "pdfUrl": "https://refex.co.in/wp-content/uploads/2025/09/RIL_Media_Release_STX_sd.pdf",
          "year": "2025-26"
        },
        {
          "title": "RIL – Outcome of Board Meeting",
          "date": "22/09/2025",
          "pdfUrl": "https://refex.co.in/wp-content/uploads/2025/09/RIL_STXIntimationforCompositeScheme_F_22092025_sd.pdf",
          "year": "2025-26"
        },
        {
          "title": "RIL – Incorporation of WOS – Refex Mobility Limited",
          "date": "12/09/2025",
          "pdfUrl": "https://refex.co.in/wp-content/uploads/2025/09/RIL_STX_Intimation-for-Incorporation_RML_Sep-12-2025_s.pdf",
          "year": "2025-26"
        },
        {
          "title": "RIL- Reg 30 – Allotment of OCD by Venwind Refex Power Limited – 06/09/2025",
          "date": "06/09/2025",
          "pdfUrl": "https://refex.co.in/wp-content/uploads/2025/09/RIL_STX_Intimation-for-OCD-Allotment_VRPL_06.09.2025_F.pdf",
          "year": "2025-26"
        },
        {
          "title": "RIL- Reg 30 – Bagging of Order – September 2025",
          "date": "05/09/2025",
          "pdfUrl": "https://refex.co.in/wp-content/uploads/2025/09/RIL_APPCDL_Order_sd.pdf",
          "year": "2025-26"
        },
        {
          "title": "RIL- Media Release – Q1 FY 26",
          "date": "13/08/2025",
          "pdfUrl": "https://refex.co.in/wp-content/uploads/2025/08/Reg30-Media-Release-13.08.2025.pdf",
          "year": "2025-26"
        },
        {
          "title": "RIL-Reg 30 – Bagging of Order",
          "date": "13/08/2025",
          "pdfUrl": "https://refex.co.in/wp-content/uploads/2025/08/RIL_Reg30-Disclosure-Award_of_Order_Receipt_of_Order.pdf",
          "year": "2025-26"
        },
        {
          "title": "RIL-Reg. 30 Disclosure-Outcome of Board Meeting",
          "date": "12/08/2025",
          "pdfUrl": "https://refex.co.in/wp-content/uploads/2025/08/RIL_Reg-30-Disclosure-Outcome-of-the-Board-Meeting.pdf",
          "year": "2025-26"
        },
        {
          "title": "RIL-Reg. 30 Disclosure",
          "date": "11/08/2025",
          "pdfUrl": "https://refex.co.in/wp-content/uploads/2025/08/RIL_Reg30-Disclosure-Acquisition.pdf",
          "year": "2025-26"
        },
        {
          "title": "RIL-Media Release – RGML- Rebranding Intimation",
          "date": "11/08/2025",
          "pdfUrl": "https://refex.co.in/wp-content/uploads/2025/08/RIL-announcement-RGML-Rebranding-Intimation_11.08.2025.pdf",
          "year": "2025-26"
        },
        {
          "title": "RIL- Reg 30 – Earnings Call Intimation Q1 FY26",
          "date": "06/08/2025",
          "pdfUrl": "https://refex.co.in/wp-content/uploads/2025/08/RIL_Reg-30-Intimation-of-Earnings-Call-Q1-FY26.pdf",
          "year": "2025-26"
        },
        {
          "title": "RIL-Reg. 29-Intimation of Board Meeting",
          "date": "05/08/2025",
          "pdfUrl": "https://refex.co.in/wp-content/uploads/2025/08/RIL_Reg30-Intimation-of-Board-Meeting-05.08.2025.pdf",
          "year": "2025-26"
        },
        {
          "title": "RIL – Reg.30 – Amendment to MOA – July 2025",
          "date": "02/08/2025",
          "pdfUrl": "https://refex.co.in/wp-content/uploads/2025/08/RIL_NTPC_Order.pdf",
          "year": "2025-26"
        },
        {
          "title": "RIL – Reg.30 – Amendment to MOA – July 2025",
          "date": "18/07/2025",
          "pdfUrl": "https://refex.co.in/wp-content/uploads/2025/07/RIL_Intimation_Reg30_MOA_18072025_sd.pdf",
          "year": "2025-26"
        },
        {
          "title": "RIL – Reg 30 – Bagging of Order – July 2025",
          "date": "15/07/2025",
          "pdfUrl": "https://refex.co.in/wp-content/uploads/2025/07/Bagging-of-Order-July2025.pdf",
          "year": "2025-26"
        },
        {
          "title": "RIL – Closure of Trading Window",
          "date": "30/06/2025",
          "pdfUrl": "https://refex.co.in/wp-content/uploads/2025/06/RIL_CTW_Q1_FY26_sd.pdf",
          "year": "2025-26"
        },
        {
          "title": "RIL- Reg.30 Disclosure",
          "date": "19/06/2025",
          "pdfUrl": "https://refex.co.in/wp-content/uploads/2025/06/RIL_Reg.30_Disclosure_19.06.2025.pdf",
          "year": "2025-26"
        },
        {
          "title": "RIL – Reg.30- Disclosure",
          "date": "05/06/2025",
          "pdfUrl": "https://refex.co.in/wp-content/uploads/2025/06/RIL_ESOP_Allotment_June2025_sd.pdf",
          "year": "2025-26"
        },
        {
          "title": "RIL – Media Release – Q4 & FY 25",
          "date": "24/04/2025",
          "pdfUrl": "https://refex.co.in/wp-content/uploads/2025/04/RIL_Press_Release_FY25_sd.pdf",
          "year": "2025-26"
        },
        {
          "title": "RIL – Reg 30 – Earnings Call Intimation Q4 and Annual FY25",
          "date": "24/04/2025",
          "pdfUrl": "https://refex.co.in/wp-content/uploads/2025/04/RIL_STX_sds.pdf",
          "year": "2025-26"
        },
        {
          "title": "RIL – Media Release – RGML & EV fleet",
          "date": "17/04/2025",
          "pdfUrl": "https://refex.co.in/wp-content/uploads/2025/04/RIL_STX_Media_RGMLEV_17042025_sd.pdf",
          "year": "2025-26"
        },
        {
          "title": "RIL-Reg.30 – Appoint of SMP",
          "date": "05/04/2025",
          "pdfUrl": "https://refex.co.in/wp-content/uploads/2025/04/Reg_30_SMP_Appointment_Intimation.pdf",
          "year": "2025-26"
        },
        {
          "title": "RIL- GST Order – AP",
          "date": "03/04/2025",
          "pdfUrl": "https://refex.co.in/wp-content/uploads/2025/04/RIL_Stx_intimation_GST_02042025_sd.pdf",
          "year": "2025-26"
        },
        {
          "title": "RIL- Closure of Trading Window",
          "date": "31/03/2025",
          "pdfUrl": "https://refex.co.in/wp-content/uploads/2025/03/RIL_Trading_window_Closure_Q4FY25.pdf",
          "year": "2024-25"
        },
        {
          "title": "RIL-Reg.30 Disclosure",
          "date": "29/03/2025",
          "pdfUrl": "https://refex.co.in/wp-content/uploads/2025/03/RIL_Stx_GST_sd.pdf",
          "year": "2024-25"
        },
        {
          "title": "RIL-Reg.30 Disclosure Outcome of Board Meeting",
          "date": "28/03/2025",
          "pdfUrl": "https://refex.co.in/wp-content/uploads/2025/03/RIL_Reg30_Outcome_PB_sd.pdf",
          "year": "2024-25"
        },
        {
          "title": "RIL- RGML & Gensol – Withdrawal of Proposal",
          "date": "28/03/2025",
          "pdfUrl": "https://refex.co.in/wp-content/uploads/2025/03/RGML_Gensol_sd.pdf",
          "year": "2024-25"
        },
        {
          "title": "RIL-Reg 30 RGML and Gensol – Investor Release",
          "date": "25/03/2025",
          "pdfUrl": "https://refex.co.in/wp-content/uploads/2025/03/RIL-Exchange_Intimation-25032025.pdf",
          "year": "2024-25"
        }
      ]
    }
  ]
}

